pycounts_test_doriscai/__init__.py
pycounts_test_doriscai/plotting.py
pycounts_test_doriscai/pycounts_test_doriscai.py
pycounts_test_doriscai-1.4.0.dist-info/LICENSE
pycounts_test_doriscai-1.4.0.dist-info/METADATA
pycounts_test_doriscai-1.4.0.dist-info/WHEEL
pycounts_test_doriscai-1.4.0.dist-info/RECORD
